midea_beautiful_dehumidifier/__init__.py
midea_beautiful_dehumidifier/appliance.py
midea_beautiful_dehumidifier/cli.py
midea_beautiful_dehumidifier/cloud.py
midea_beautiful_dehumidifier/command.py
midea_beautiful_dehumidifier/crypto.py
midea_beautiful_dehumidifier/exceptions.py
midea_beautiful_dehumidifier/lan.py
midea_beautiful_dehumidifier/midea.py
midea_beautiful_dehumidifier/scanner.py
midea_beautiful_dehumidifier/util.py
midea_beautiful_dehumidifier/version.py
midea_beautiful_dehumidifier-0.6.1.dist-info/LICENSE
midea_beautiful_dehumidifier-0.6.1.dist-info/METADATA
midea_beautiful_dehumidifier-0.6.1.dist-info/WHEEL
midea_beautiful_dehumidifier-0.6.1.dist-info/entry_points.txt
midea_beautiful_dehumidifier-0.6.1.dist-info/top_level.txt
midea_beautiful_dehumidifier-0.6.1.dist-info/RECORD
