Metadata-Version: 2.1
Name: midea-beautiful-dehumidifier
Version: 0.6.1
Summary: A library to control Midea dehumidifiers via the Local area network
Home-page: https://github.com/nbogojevic/midea-beautiful-dehumidifier
Author: Nenad Bogojević
Author-email: nenad.bogojevic@gmail.com
License: MIT
Platform: UNKNOWN
Classifier: Intended Audience :: Developers
Classifier: License :: OSI Approved :: MIT License
Classifier: Operating System :: MacOS :: MacOS X
Classifier: Operating System :: Microsoft :: Windows
Classifier: Operating System :: POSIX :: Linux
Classifier: Programming Language :: Python :: 3
Classifier: Topic :: Home Automation
License-File: LICENSE
Requires-Dist: cryptography (>=3.4)
Requires-Dist: requests (>=2.25.1)
Requires-Dist: ifaddr (>=0.1.7)
